nerlogparser/nerlogparser.py
nerlogparser/__pycache__/nerlogparser.cpython-35.pyc
nerlogparser/data/chars.txt
nerlogparser/data/glove.6B.300d.trimmed.npz
nerlogparser/data/label.txt
nerlogparser/data/tags.txt
nerlogparser/data/test.txt
nerlogparser/data/words.txt
nerlogparser/dataformat/__init__.py
nerlogparser/dataformat/toconll.py
nerlogparser/grammar/__init__.py
nerlogparser/grammar/authlog.py
nerlogparser/grammar/bluegenelog.py
nerlogparser/grammar/csvlog.py
nerlogparser/grammar/daemonlog.py
nerlogparser/grammar/debuglog.py
nerlogparser/grammar/dmesglog.py
nerlogparser/grammar/grammar_utility.py
nerlogparser/grammar/kernellog.py
nerlogparser/grammar/kippolog.py
nerlogparser/grammar/messageslog.py
nerlogparser/grammar/proxifierlog.py
nerlogparser/grammar/weblog.py
nerlogparser/grammar/zookeeperlog.py
nerlogparser/model/__init__.py
nerlogparser/model/base_model.py
nerlogparser/model/build_data.py
nerlogparser/model/config.py
nerlogparser/model/data_utils.py
nerlogparser/model/evaluate.py
nerlogparser/model/general_utils.py
nerlogparser/model/ner_model.py
nerlogparser/model/train.py
nerlogparser/model/__pycache__/__init__.cpython-35.pyc
nerlogparser/model/__pycache__/base_model.cpython-35.pyc
nerlogparser/model/__pycache__/config.cpython-35.pyc
nerlogparser/model/__pycache__/data_utils.cpython-35.pyc
nerlogparser/model/__pycache__/general_utils.cpython-35.pyc
nerlogparser/model/__pycache__/ner_model.cpython-35.pyc
nerlogparser/output/__init__.py
nerlogparser/output/to_json.py
nerlogparser/output/__pycache__/__init__.cpython-35.pyc
nerlogparser/output/__pycache__/to_json.cpython-35.pyc
nerlogparser/preprocessing/Preprocessing.py
nerlogparser/preprocessing/Splitting.py
nerlogparser/preprocessing/__init__.py
nerlogparser/preprocessing/config/datasets.conf
nerlogparser/results/test/events.out.tfevents.1533503273.seitpc80
nerlogparser/results/test/log.txt
nerlogparser/results/test/model.weights/.data-00000-of-00001
nerlogparser-0.0.1.dist-info/METADATA
nerlogparser-0.0.1.dist-info/RECORD
nerlogparser-0.0.1.dist-info/WHEEL
nerlogparser-0.0.1.dist-info/entry_points.txt
nerlogparser-0.0.1.dist-info/top_level.txt
